virgiledassonneville_picsou/__init__.py
virgiledassonneville_picsou/picsou.py
virgiledassonneville_picsou-0.1.0.dist-info/METADATA
virgiledassonneville_picsou-0.1.0.dist-info/WHEEL
virgiledassonneville_picsou-0.1.0.dist-info/RECORD
